odoo/addons/pms_api_rest/README.rst
odoo/addons/pms_api_rest/__init__.py
odoo/addons/pms_api_rest/__manifest__.py
odoo/addons/pms_api_rest/http.py
odoo/addons/pms_api_rest/pms_api_rest_utils.py
odoo/addons/pms_api_rest/controllers/__init__.py
odoo/addons/pms_api_rest/controllers/pms_rest.py
odoo/addons/pms_api_rest/data/auth_jwt_validator.xml
odoo/addons/pms_api_rest/data/cron_jobs.xml
odoo/addons/pms_api_rest/data/pms_app_reset_password_template.xml
odoo/addons/pms_api_rest/data/sql_reports.xml
odoo/addons/pms_api_rest/datamodels/__init__.py
odoo/addons/pms_api_rest/datamodels/feed_post.py
odoo/addons/pms_api_rest/datamodels/pms_account_journal.py
odoo/addons/pms_api_rest/datamodels/pms_account_payment_term.py
odoo/addons/pms_api_rest/datamodels/pms_agency.py
odoo/addons/pms_api_rest/datamodels/pms_amenity.py
odoo/addons/pms_api_rest/datamodels/pms_amenity_type.py
odoo/addons/pms_api_rest/datamodels/pms_avail.py
odoo/addons/pms_api_rest/datamodels/pms_availability_plan.py
odoo/addons/pms_api_rest/datamodels/pms_availability_plan_rule.py
odoo/addons/pms_api_rest/datamodels/pms_board_service.py
odoo/addons/pms_api_rest/datamodels/pms_board_service_line.py
odoo/addons/pms_api_rest/datamodels/pms_calendar.py
odoo/addons/pms_api_rest/datamodels/pms_cancelation_rule.py
odoo/addons/pms_api_rest/datamodels/pms_cash_register.py
odoo/addons/pms_api_rest/datamodels/pms_checkin_partner.py
odoo/addons/pms_api_rest/datamodels/pms_dashboard.py
odoo/addons/pms_api_rest/datamodels/pms_extra_bed.py
odoo/addons/pms_api_rest/datamodels/pms_folio.py
odoo/addons/pms_api_rest/datamodels/pms_folio_sale_line.py
odoo/addons/pms_api_rest/datamodels/pms_id_category.py
odoo/addons/pms_api_rest/datamodels/pms_invoice.py
odoo/addons/pms_api_rest/datamodels/pms_invoice_line.py
odoo/addons/pms_api_rest/datamodels/pms_mail.py
odoo/addons/pms_api_rest/datamodels/pms_notification.py
odoo/addons/pms_api_rest/datamodels/pms_ocr.py
odoo/addons/pms_api_rest/datamodels/pms_partner.py
odoo14_addon_pms_api_rest-14.0.1.0.1.dev580.dist-info/METADATA
odoo14_addon_pms_api_rest-14.0.1.0.1.dev580.dist-info/WHEEL
odoo14_addon_pms_api_rest-14.0.1.0.1.dev580.dist-info/top_level.txt
odoo14_addon_pms_api_rest-14.0.1.0.1.dev580.dist-info/RECORD
