Metadata-Version: 2.1
Name: odoo14-addon-pms_api_rest
Version: 14.0.1.0.1.dev580
Summary: API REST PMS
Home-page: https://github.com/OCA/pms
Author: Commit [Sun], Odoo Community Association (OCA)
Author-email: support@odoo-community.org
License: AGPL-3
Classifier: Programming Language :: Python
Classifier: Framework :: Odoo
Classifier: Framework :: Odoo :: 14.0
Classifier: License :: OSI Approved :: GNU Affero General Public License v3
Requires-Python: >=3.6
Requires-Dist: jose
Requires-Dist: jwt
Requires-Dist: marshmallow
Requires-Dist: odoo14-addon-auth-jwt-login
Requires-Dist: odoo14-addon-base-location
Requires-Dist: odoo14-addon-base-rest
Requires-Dist: odoo14-addon-base-rest-datamodel
Requires-Dist: odoo14-addon-feed-rss
Requires-Dist: odoo14-addon-l10n-es-aeat
Requires-Dist: odoo14-addon-pms
Requires-Dist: odoo14-addon-sql-export-excel
Requires-Dist: odoo<14.1dev,>=14.0a
Requires-Dist: simplejson
